main.py
pybroadcast-0.0.1.dist-info/METADATA
pybroadcast-0.0.1.dist-info/WHEEL
pybroadcast-0.0.1.dist-info/top_level.txt
pybroadcast-0.0.1.dist-info/RECORD
