Metadata-Version: 2.4
Name: pybroadcast
Version: 0.0.1
Summary: Add your description here
Requires-Python: >=3.13
Requires-Dist: fastapi>=0.115.12
Requires-Dist: mutagen>=1.47.0
Requires-Dist: uvicorn>=0.34.2
